{
    "error_id": "714",
    "information": {
        "errors": [
            {
                "line": "19",
                "severity": "warning",
                "message": "'package' should be separated from previous statement.",
                "source": "com.puppycrawl.tools.checkstyle.checks.whitespace.EmptyLineSeparatorCheck"
            }
        ]
    },
    "source_code": " * under the License.\n */\npackage org.apache.iotdb.tsfile.v1.file.metadata.statistics;\n\nimport java.io.IOException;\nimport java.io.InputStream;",
    "results": [
        {
            "tool": "styler",
            "errors": [],
            "diff": "diff --git a/home/thomas/mnt/fernanda/styler-test2/python/./experiments/projects/../results/apache-incubator-iotdb/errored/1/714/BinaryStatisticsV1.java b/home/thomas/mnt/fernanda/styler-test2/python/./experiments/projects/../results/apache-incubator-iotdb/styler/714/BinaryStatisticsV1.java\nindex 3c68be1326..9dbca4bf90 100644\n--- a/home/thomas/mnt/fernanda/styler-test2/python/./experiments/projects/../results/apache-incubator-iotdb/errored/1/714/BinaryStatisticsV1.java\n+++ b/home/thomas/mnt/fernanda/styler-test2/python/./experiments/projects/../results/apache-incubator-iotdb/styler/714/BinaryStatisticsV1.java\n@@ -16,6 +16,7 @@\n  * specific language governing permissions and limitations\n  * under the License.\n  */\n+\n package org.apache.iotdb.tsfile.v1.file.metadata.statistics;\n \n import java.io.IOException;\n",
            "diff_size": 1
        },
        {
            "tool": "intellij",
            "errors": [],
            "diff": "diff --git a/home/thomas/mnt/fernanda/styler-test2/python/./experiments/projects/../results/apache-incubator-iotdb/errored/1/714/BinaryStatisticsV1.java b/home/thomas/mnt/fernanda/styler-test2/python/./experiments/projects/../results/apache-incubator-iotdb/intellij/714/BinaryStatisticsV1.java\nindex 3c68be1326..9dbca4bf90 100644\n--- a/home/thomas/mnt/fernanda/styler-test2/python/./experiments/projects/../results/apache-incubator-iotdb/errored/1/714/BinaryStatisticsV1.java\n+++ b/home/thomas/mnt/fernanda/styler-test2/python/./experiments/projects/../results/apache-incubator-iotdb/intellij/714/BinaryStatisticsV1.java\n@@ -16,6 +16,7 @@\n  * specific language governing permissions and limitations\n  * under the License.\n  */\n+\n package org.apache.iotdb.tsfile.v1.file.metadata.statistics;\n \n import java.io.IOException;\n",
            "diff_size": 1
        },
        {
            "tool": "naturalize",
            "errors": [
                {
                    "line": "19",
                    "severity": "warning",
                    "message": "'package' should be separated from previous statement.",
                    "source": "com.puppycrawl.tools.checkstyle.checks.whitespace.EmptyLineSeparatorCheck"
                },
                {
                    "line": "63",
                    "severity": "warning",
                    "message": "Line is longer than 100 characters (found 104).",
                    "source": "com.puppycrawl.tools.checkstyle.checks.sizes.LineLengthCheck"
                },
                {
                    "line": "64",
                    "severity": "warning",
                    "message": "'method def' child has incorrect indentation level 0, expected level should be 4.",
                    "source": "com.puppycrawl.tools.checkstyle.checks.indentation.IndentationCheck"
                },
                {
                    "line": "65",
                    "severity": "warning",
                    "message": "'method def' child has incorrect indentation level 0, expected level should be 4.",
                    "source": "com.puppycrawl.tools.checkstyle.checks.indentation.IndentationCheck"
                },
                {
                    "line": "65",
                    "severity": "warning",
                    "message": "Line is longer than 100 characters (found 102).",
                    "source": "com.puppycrawl.tools.checkstyle.checks.sizes.LineLengthCheck"
                },
                {
                    "line": "66",
                    "severity": "warning",
                    "message": "'method def' child has incorrect indentation level 0, expected level should be 4.",
                    "source": "com.puppycrawl.tools.checkstyle.checks.indentation.IndentationCheck"
                },
                {
                    "line": "66",
                    "severity": "warning",
                    "message": "Line is longer than 100 characters (found 101).",
                    "source": "com.puppycrawl.tools.checkstyle.checks.sizes.LineLengthCheck"
                },
                {
                    "line": "67",
                    "severity": "warning",
                    "message": "'method def' child has incorrect indentation level 0, expected level should be 4.",
                    "source": "com.puppycrawl.tools.checkstyle.checks.indentation.IndentationCheck"
                }
            ],
            "diff": "diff --git a/home/thomas/mnt/fernanda/styler-test2/python/./experiments/projects/../results/apache-incubator-iotdb/errored/1/714/BinaryStatisticsV1.java b/home/thomas/mnt/fernanda/styler-test2/python/./experiments/projects/../results/apache-incubator-iotdb/naturalize/714/BinaryStatisticsV1.java\nindex 3c68be1326..3a8abf81f6 100644\n--- a/home/thomas/mnt/fernanda/styler-test2/python/./experiments/projects/../results/apache-incubator-iotdb/errored/1/714/BinaryStatisticsV1.java\n+++ b/home/thomas/mnt/fernanda/styler-test2/python/./experiments/projects/../results/apache-incubator-iotdb/naturalize/714/BinaryStatisticsV1.java\n@@ -28,7 +28,6 @@ import org.apache.iotdb.tsfile.utils.ReadWriteIOUtils;\n  * Statistics for string type.\n  */\n public class BinaryStatisticsV1 extends StatisticsV1<Binary> {\n-\n   private Binary min = new Binary(\"\");\n   private Binary max = new Binary(\"\");\n   private Binary first = new Binary(\"\");\n@@ -60,25 +59,19 @@ public class BinaryStatisticsV1 extends StatisticsV1<Binary> {\n     return sum;\n   }\n \n-  @Override\n-  void deserialize(ByteBuffer byteBuffer) throws IOException {\n-    this.min = new Binary(\n-        ReadWriteIOUtils.readByteBufferWithSelfDescriptionLength(byteBuffer).array());\n-    this.max = new Binary(\n-        ReadWriteIOUtils.readByteBufferWithSelfDescriptionLength(byteBuffer).array());\n-    this.first = new Binary(\n-        ReadWriteIOUtils.readByteBufferWithSelfDescriptionLength(byteBuffer).array());\n-    this.last = new Binary(\n-        ReadWriteIOUtils.readByteBufferWithSelfDescriptionLength(byteBuffer).array());\n-    this.sum = ReadWriteIOUtils.readDouble(byteBuffer);\n+  @Override void deserialize(ByteBuffer byteBuffer) throws IOException {\n+    this.min = new Binary(ReadWriteIOUtils.readByteBufferWithSelfDescriptionLength(byteBuffer).array());\n+this.max = new Binary(ReadWriteIOUtils.readByteBufferWithSelfDescriptionLength(byteBuffer).array());\n+this.first = new Binary(ReadWriteIOUtils.readByteBufferWithSelfDescriptionLength(byteBuffer).array());\n+this.last = new Binary(ReadWriteIOUtils.readByteBufferWithSelfDescriptionLength(byteBuffer).array());\n+this.sum = ReadWriteIOUtils.readDouble(byteBuffer);\n   }\n \n-  @Override\n-  void deserialize(InputStream inputStream) throws IOException {\n+  @Override void deserialize(InputStream inputStream) throws IOException {\n     this.min = new Binary(ReadWriteIOUtils.readBytesWithSelfDescriptionLength(inputStream));\n     this.max = new Binary(ReadWriteIOUtils.readBytesWithSelfDescriptionLength(inputStream));\n     this.first = new Binary(ReadWriteIOUtils.readBytesWithSelfDescriptionLength(inputStream));\n     this.last = new Binary(ReadWriteIOUtils.readBytesWithSelfDescriptionLength(inputStream));\n     this.sum = ReadWriteIOUtils.readDouble(inputStream);\n   }\n-}\n+}\n\\ No newline at end of file\n",
            "diff_size": 15
        },
        {
            "tool": "codebuff",
            "errors": [
                {
                    "line": "19",
                    "severity": "warning",
                    "message": "'package' should be separated from previous statement.",
                    "source": "com.puppycrawl.tools.checkstyle.checks.whitespace.EmptyLineSeparatorCheck"
                },
                {
                    "line": "20",
                    "severity": "warning",
                    "message": "'import' should be separated from previous statement.",
                    "source": "com.puppycrawl.tools.checkstyle.checks.whitespace.EmptyLineSeparatorCheck"
                },
                {
                    "line": "30",
                    "column": "54",
                    "severity": "warning",
                    "message": "GenericWhitespace '<' is followed by whitespace.",
                    "source": "com.puppycrawl.tools.checkstyle.checks.whitespace.GenericWhitespaceCheck"
                },
                {
                    "line": "30",
                    "column": "54",
                    "severity": "warning",
                    "message": "GenericWhitespace '<' is preceded with whitespace.",
                    "source": "com.puppycrawl.tools.checkstyle.checks.whitespace.GenericWhitespaceCheck"
                },
                {
                    "line": "33",
                    "severity": "warning",
                    "message": "'member def modifier' has incorrect indentation level 4, expected level should be 2.",
                    "source": "com.puppycrawl.tools.checkstyle.checks.indentation.IndentationCheck"
                },
                {
                    "line": "36",
                    "severity": "warning",
                    "message": "'member def modifier' has incorrect indentation level 4, expected level should be 2.",
                    "source": "com.puppycrawl.tools.checkstyle.checks.indentation.IndentationCheck"
                },
                {
                    "line": "39",
                    "severity": "warning",
                    "message": "'member def modifier' has incorrect indentation level 4, expected level should be 2.",
                    "source": "com.puppycrawl.tools.checkstyle.checks.indentation.IndentationCheck"
                },
                {
                    "line": "42",
                    "severity": "warning",
                    "message": "'member def modifier' has incorrect indentation level 4, expected level should be 2.",
                    "source": "com.puppycrawl.tools.checkstyle.checks.indentation.IndentationCheck"
                },
                {
                    "line": "45",
                    "severity": "warning",
                    "message": "'member def modifier' has incorrect indentation level 4, expected level should be 2.",
                    "source": "com.puppycrawl.tools.checkstyle.checks.indentation.IndentationCheck"
                },
                {
                    "line": "48",
                    "severity": "warning",
                    "message": "'method def modifier' has incorrect indentation level 4, expected level should be 2.",
                    "source": "com.puppycrawl.tools.checkstyle.checks.indentation.IndentationCheck"
                },
                {
                    "line": "50",
                    "severity": "warning",
                    "message": "'method def rcurly' has incorrect indentation level 4, expected level should be 2.",
                    "source": "com.puppycrawl.tools.checkstyle.checks.indentation.IndentationCheck"
                },
                {
                    "line": "52",
                    "severity": "warning",
                    "message": "'method def modifier' has incorrect indentation level 4, expected level should be 2.",
                    "source": "com.puppycrawl.tools.checkstyle.checks.indentation.IndentationCheck"
                },
                {
                    "line": "54",
                    "severity": "warning",
                    "message": "'method def rcurly' has incorrect indentation level 4, expected level should be 2.",
                    "source": "com.puppycrawl.tools.checkstyle.checks.indentation.IndentationCheck"
                },
                {
                    "line": "56",
                    "severity": "warning",
                    "message": "'method def modifier' has incorrect indentation level 4, expected level should be 2.",
                    "source": "com.puppycrawl.tools.checkstyle.checks.indentation.IndentationCheck"
                },
                {
                    "line": "58",
                    "severity": "warning",
                    "message": "'method def rcurly' has incorrect indentation level 4, expected level should be 2.",
                    "source": "com.puppycrawl.tools.checkstyle.checks.indentation.IndentationCheck"
                },
                {
                    "line": "60",
                    "severity": "warning",
                    "message": "'method def modifier' has incorrect indentation level 4, expected level should be 2.",
                    "source": "com.puppycrawl.tools.checkstyle.checks.indentation.IndentationCheck"
                },
                {
                    "line": "62",
                    "severity": "warning",
                    "message": "'method def rcurly' has incorrect indentation level 4, expected level should be 2.",
                    "source": "com.puppycrawl.tools.checkstyle.checks.indentation.IndentationCheck"
                },
                {
                    "line": "64",
                    "severity": "warning",
                    "message": "'method def modifier' has incorrect indentation level 4, expected level should be 2.",
                    "source": "com.puppycrawl.tools.checkstyle.checks.indentation.IndentationCheck"
                },
                {
                    "line": "66",
                    "severity": "warning",
                    "message": "'method def rcurly' has incorrect indentation level 4, expected level should be 2.",
                    "source": "com.puppycrawl.tools.checkstyle.checks.indentation.IndentationCheck"
                },
                {
                    "line": "68",
                    "severity": "warning",
                    "message": "'method def modifier' has incorrect indentation level 4, expected level should be 2.",
                    "source": "com.puppycrawl.tools.checkstyle.checks.indentation.IndentationCheck"
                },
                {
                    "line": "69",
                    "severity": "warning",
                    "message": "Line is longer than 100 characters (found 104).",
                    "source": "com.puppycrawl.tools.checkstyle.checks.sizes.LineLengthCheck"
                },
                {
                    "line": "70",
                    "severity": "warning",
                    "message": "Line is longer than 100 characters (found 104).",
                    "source": "com.puppycrawl.tools.checkstyle.checks.sizes.LineLengthCheck"
                },
                {
                    "line": "71",
                    "severity": "warning",
                    "message": "Line is longer than 100 characters (found 106).",
                    "source": "com.puppycrawl.tools.checkstyle.checks.sizes.LineLengthCheck"
                },
                {
                    "line": "72",
                    "severity": "warning",
                    "message": "Line is longer than 100 characters (found 105).",
                    "source": "com.puppycrawl.tools.checkstyle.checks.sizes.LineLengthCheck"
                },
                {
                    "line": "74",
                    "severity": "warning",
                    "message": "'method def rcurly' has incorrect indentation level 4, expected level should be 2.",
                    "source": "com.puppycrawl.tools.checkstyle.checks.indentation.IndentationCheck"
                },
                {
                    "line": "76",
                    "severity": "warning",
                    "message": "'method def modifier' has incorrect indentation level 4, expected level should be 2.",
                    "source": "com.puppycrawl.tools.checkstyle.checks.indentation.IndentationCheck"
                },
                {
                    "line": "82",
                    "severity": "warning",
                    "message": "'method def rcurly' has incorrect indentation level 4, expected level should be 2.",
                    "source": "com.puppycrawl.tools.checkstyle.checks.indentation.IndentationCheck"
                }
            ],
            "diff": "diff --git a/home/thomas/mnt/fernanda/styler-test2/python/./experiments/projects/../results/apache-incubator-iotdb/errored/1/714/BinaryStatisticsV1.java b/home/thomas/mnt/fernanda/styler-test2/python/./experiments/projects/../results/apache-incubator-iotdb/codebuff/714/BinaryStatisticsV1.java\nindex 3c68be1326..b2c5b68b47 100644\n--- a/home/thomas/mnt/fernanda/styler-test2/python/./experiments/projects/../results/apache-incubator-iotdb/errored/1/714/BinaryStatisticsV1.java\n+++ b/home/thomas/mnt/fernanda/styler-test2/python/./experiments/projects/../results/apache-incubator-iotdb/codebuff/714/BinaryStatisticsV1.java\n@@ -17,7 +17,6 @@\n  * under the License.\n  */\n package org.apache.iotdb.tsfile.v1.file.metadata.statistics;\n-\n import java.io.IOException;\n import java.io.InputStream;\n import java.nio.ByteBuffer;\n@@ -27,58 +26,59 @@ import org.apache.iotdb.tsfile.utils.ReadWriteIOUtils;\n /**\n  * Statistics for string type.\n  */\n-public class BinaryStatisticsV1 extends StatisticsV1<Binary> {\n \n-  private Binary min = new Binary(\"\");\n-  private Binary max = new Binary(\"\");\n-  private Binary first = new Binary(\"\");\n-  private Binary last = new Binary(\"\");\n-  private double sum;\n+public class BinaryStatisticsV1 extends StatisticsV1 < Binary> {\n+\n+\n+    private Binary min = new Binary(\"\");\n+\n+\n+    private Binary max = new Binary(\"\");\n+\n+\n+    private Binary first = new Binary(\"\");\n \n-  @Override\n-  public Binary getMin() {\n+\n+    private Binary last = new Binary(\"\");\n+\n+\n+    private double sum;\n+\n+\n+    @ Override public Binary getMin() {\n     return min;\n-  }\n+    }\n \n-  @Override\n-  public Binary getMax() {\n+    @ Override public Binary getMax() {\n     return max;\n-  }\n+    }\n \n-  @Override\n-  public Binary getFirst() {\n+    @ Override public Binary getFirst() {\n     return first;\n-  }\n+    }\n \n-  @Override\n-  public Binary getLast() {\n+    @ Override public Binary getLast() {\n     return last;\n-  }\n+    }\n \n-  @Override\n-  public double getSum() {\n+    @ Override public double getSum() {\n     return sum;\n-  }\n-\n-  @Override\n-  void deserialize(ByteBuffer byteBuffer) throws IOException {\n-    this.min = new Binary(\n-        ReadWriteIOUtils.readByteBufferWithSelfDescriptionLength(byteBuffer).array());\n-    this.max = new Binary(\n-        ReadWriteIOUtils.readByteBufferWithSelfDescriptionLength(byteBuffer).array());\n-    this.first = new Binary(\n-        ReadWriteIOUtils.readByteBufferWithSelfDescriptionLength(byteBuffer).array());\n-    this.last = new Binary(\n-        ReadWriteIOUtils.readByteBufferWithSelfDescriptionLength(byteBuffer).array());\n+    }\n+\n+    @ Override void deserialize(ByteBuffer byteBuffer) throws IOException {\n+    this.min = new Binary(ReadWriteIOUtils.readByteBufferWithSelfDescriptionLength(byteBuffer).array());\n+    this.max = new Binary(ReadWriteIOUtils.readByteBufferWithSelfDescriptionLength(byteBuffer).array());\n+    this.first = new Binary(ReadWriteIOUtils.readByteBufferWithSelfDescriptionLength(byteBuffer).array());\n+    this.last = new Binary(ReadWriteIOUtils.readByteBufferWithSelfDescriptionLength(byteBuffer).array());\n     this.sum = ReadWriteIOUtils.readDouble(byteBuffer);\n-  }\n+    }\n \n-  @Override\n-  void deserialize(InputStream inputStream) throws IOException {\n+    @ Override void deserialize(InputStream inputStream) throws IOException {\n     this.min = new Binary(ReadWriteIOUtils.readBytesWithSelfDescriptionLength(inputStream));\n     this.max = new Binary(ReadWriteIOUtils.readBytesWithSelfDescriptionLength(inputStream));\n     this.first = new Binary(ReadWriteIOUtils.readBytesWithSelfDescriptionLength(inputStream));\n     this.last = new Binary(ReadWriteIOUtils.readBytesWithSelfDescriptionLength(inputStream));\n     this.sum = ReadWriteIOUtils.readDouble(inputStream);\n-  }\n-}\n+    }\n+\n+}\n\\ No newline at end of file\n",
            "diff_size": 50
        },
        {
            "tool": "styler_random",
            "errors": [
                {
                    "line": "19",
                    "severity": "warning",
                    "message": "'package' should be separated from previous statement.",
                    "source": "com.puppycrawl.tools.checkstyle.checks.whitespace.EmptyLineSeparatorCheck"
                }
            ],
            "diff": "",
            "diff_size": 0
        },
        {
            "tool": "styler_three_grams",
            "errors": [],
            "diff": "diff --git a/home/thomas/mnt/fernanda/styler-test2/python/./experiments/projects/../results/apache-incubator-iotdb/errored/1/714/BinaryStatisticsV1.java b/home/thomas/mnt/fernanda/styler-test2/python/./experiments/projects/../results/apache-incubator-iotdb/styler_three_grams/714/BinaryStatisticsV1.java\nindex 3c68be1326..9dbca4bf90 100644\n--- a/home/thomas/mnt/fernanda/styler-test2/python/./experiments/projects/../results/apache-incubator-iotdb/errored/1/714/BinaryStatisticsV1.java\n+++ b/home/thomas/mnt/fernanda/styler-test2/python/./experiments/projects/../results/apache-incubator-iotdb/styler_three_grams/714/BinaryStatisticsV1.java\n@@ -16,6 +16,7 @@\n  * specific language governing permissions and limitations\n  * under the License.\n  */\n+\n package org.apache.iotdb.tsfile.v1.file.metadata.statistics;\n \n import java.io.IOException;\n",
            "diff_size": 1
        }
    ]
}