{
    "error_id": "115",
    "information": {
        "errors": [
            {
                "line": "47",
                "column": "1",
                "severity": "error",
                "message": "File contains tab characters (this is the first instance).",
                "source": "com.puppycrawl.tools.checkstyle.checks.whitespace.FileTabCharacterCheck"
            }
        ]
    },
    "source_code": " */\npublic interface HTMLMetaElement extends HTMLElement {\n\t/**\n\t * Associated information. See the content attribute definition in HTML 4.01.\n\t *\n\t * @return a {@link java.lang.String} object.",
    "results": [
        {
            "tool": "styler",
            "errors": [
                {
                    "line": "48",
                    "column": "1",
                    "severity": "error",
                    "message": "File contains tab characters (this is the first instance).",
                    "source": "com.puppycrawl.tools.checkstyle.checks.whitespace.FileTabCharacterCheck"
                }
            ],
            "diff": "diff --git a/home/thomas/mnt/fernanda/styler-test2/python/./experiments/projects/../results/LoboEvolution-LoboEvolution/errored/1/115/HTMLMetaElement.java b/home/thomas/mnt/fernanda/styler-test2/python/./experiments/projects/../results/LoboEvolution-LoboEvolution/styler/115/HTMLMetaElement.java\nindex 6e6e51884b..71cf1a3909 100644\n--- a/home/thomas/mnt/fernanda/styler-test2/python/./experiments/projects/../results/LoboEvolution-LoboEvolution/errored/1/115/HTMLMetaElement.java\n+++ b/home/thomas/mnt/fernanda/styler-test2/python/./experiments/projects/../results/LoboEvolution-LoboEvolution/styler/115/HTMLMetaElement.java\n@@ -44,7 +44,7 @@ package org.loboevolution.html.dom;\n  * @version $Id: $Id\n  */\n public interface HTMLMetaElement extends HTMLElement {\n-\t/**\n+/**\n \t * Associated information. See the content attribute definition in HTML 4.01.\n \t *\n \t * @return a {@link java.lang.String} object.\n",
            "diff_size": 1
        },
        {
            "tool": "intellij",
            "errors": [],
            "diff": "diff --git a/home/thomas/mnt/fernanda/styler-test2/python/./experiments/projects/../results/LoboEvolution-LoboEvolution/errored/1/115/HTMLMetaElement.java b/home/thomas/mnt/fernanda/styler-test2/python/./experiments/projects/../results/LoboEvolution-LoboEvolution/intellij/115/HTMLMetaElement.java\nindex 6e6e51884b..781ce4ea30 100644\n--- a/home/thomas/mnt/fernanda/styler-test2/python/./experiments/projects/../results/LoboEvolution-LoboEvolution/errored/1/115/HTMLMetaElement.java\n+++ b/home/thomas/mnt/fernanda/styler-test2/python/./experiments/projects/../results/LoboEvolution-LoboEvolution/intellij/115/HTMLMetaElement.java\n@@ -44,62 +44,62 @@ package org.loboevolution.html.dom;\n  * @version $Id: $Id\n  */\n public interface HTMLMetaElement extends HTMLElement {\n-\t/**\n-\t * Associated information. See the content attribute definition in HTML 4.01.\n-\t *\n-\t * @return a {@link java.lang.String} object.\n-\t */\n-\tString getContent();\n+  /**\n+   * Associated information. See the content attribute definition in HTML 4.01.\n+   *\n+   * @return a {@link java.lang.String} object.\n+   */\n+  String getContent();\n \n-\t/**\n-\t * HTTP response header name [<a href='http://www.ietf.org/rfc/rfc2616.txt'>IETF\n-\t * RFC 2616</a>]. See the http-equiv attribute definition in HTML 4.01.\n-\t *\n-\t * @return a {@link java.lang.String} object.\n-\t */\n-\tString getHttpEquiv();\n+  /**\n+   * HTTP response header name [<a href='http://www.ietf.org/rfc/rfc2616.txt'>IETF\n+   * RFC 2616</a>]. See the http-equiv attribute definition in HTML 4.01.\n+   *\n+   * @return a {@link java.lang.String} object.\n+   */\n+  String getHttpEquiv();\n \n-\t/**\n-\t * Meta information name. See the name attribute definition in HTML 4.01.\n-\t *\n-\t * @return a {@link java.lang.String} object.\n-\t */\n-\tString getName();\n+  /**\n+   * Meta information name. See the name attribute definition in HTML 4.01.\n+   *\n+   * @return a {@link java.lang.String} object.\n+   */\n+  String getName();\n \n-\t/**\n-\t * Select form of content. See the scheme attribute definition in HTML 4.01.\n-\t *\n-\t * @return a {@link java.lang.String} object.\n-\t */\n-\tString getScheme();\n+  /**\n+   * Select form of content. See the scheme attribute definition in HTML 4.01.\n+   *\n+   * @return a {@link java.lang.String} object.\n+   */\n+  String getScheme();\n \n-\t/**\n-\t * Associated information. See the content attribute definition in HTML 4.01.\n-\t *\n-\t * @param content a {@link java.lang.String} object.\n-\t */\n-\tvoid setContent(String content);\n+  /**\n+   * Associated information. See the content attribute definition in HTML 4.01.\n+   *\n+   * @param content a {@link java.lang.String} object.\n+   */\n+  void setContent(String content);\n \n-\t/**\n-\t * HTTP response header name [<a href='http://www.ietf.org/rfc/rfc2616.txt'>IETF\n-\t * RFC 2616</a>]. See the http-equiv attribute definition in HTML 4.01.\n-\t *\n-\t * @param httpEquiv a {@link java.lang.String} object.\n-\t */\n-\tvoid setHttpEquiv(String httpEquiv);\n+  /**\n+   * HTTP response header name [<a href='http://www.ietf.org/rfc/rfc2616.txt'>IETF\n+   * RFC 2616</a>]. See the http-equiv attribute definition in HTML 4.01.\n+   *\n+   * @param httpEquiv a {@link java.lang.String} object.\n+   */\n+  void setHttpEquiv(String httpEquiv);\n \n-\t/**\n-\t * Meta information name. See the name attribute definition in HTML 4.01.\n-\t *\n-\t * @param name a {@link java.lang.String} object.\n-\t */\n-\tvoid setName(String name);\n+  /**\n+   * Meta information name. See the name attribute definition in HTML 4.01.\n+   *\n+   * @param name a {@link java.lang.String} object.\n+   */\n+  void setName(String name);\n \n-\t/**\n-\t * Select form of content. See the scheme attribute definition in HTML 4.01.\n-\t *\n-\t * @param scheme a {@link java.lang.String} object.\n-\t */\n-\tvoid setScheme(String scheme);\n+  /**\n+   * Select form of content. See the scheme attribute definition in HTML 4.01.\n+   *\n+   * @param scheme a {@link java.lang.String} object.\n+   */\n+  void setScheme(String scheme);\n \n }\n",
            "diff_size": 50
        },
        {
            "tool": "naturalize",
            "errors": null,
            "diff": null
        },
        {
            "tool": "codebuff",
            "errors": [],
            "diff": "diff --git a/home/thomas/mnt/fernanda/styler-test2/python/./experiments/projects/../results/LoboEvolution-LoboEvolution/errored/1/115/HTMLMetaElement.java b/home/thomas/mnt/fernanda/styler-test2/python/./experiments/projects/../results/LoboEvolution-LoboEvolution/codebuff/115/HTMLMetaElement.java\nindex 6e6e51884b..98e850836b 100644\n--- a/home/thomas/mnt/fernanda/styler-test2/python/./experiments/projects/../results/LoboEvolution-LoboEvolution/errored/1/115/HTMLMetaElement.java\n+++ b/home/thomas/mnt/fernanda/styler-test2/python/./experiments/projects/../results/LoboEvolution-LoboEvolution/codebuff/115/HTMLMetaElement.java\n@@ -43,63 +43,80 @@ package org.loboevolution.html.dom;\n  * @author utente\n  * @version $Id: $Id\n  */\n+\n+\n public interface HTMLMetaElement extends HTMLElement {\n-\t/**\n-\t * Associated information. See the content attribute definition in HTML 4.01.\n-\t *\n-\t * @return a {@link java.lang.String} object.\n-\t */\n-\tString getContent();\n-\n-\t/**\n-\t * HTTP response header name [<a href='http://www.ietf.org/rfc/rfc2616.txt'>IETF\n-\t * RFC 2616</a>]. See the http-equiv attribute definition in HTML 4.01.\n-\t *\n-\t * @return a {@link java.lang.String} object.\n-\t */\n-\tString getHttpEquiv();\n-\n-\t/**\n-\t * Meta information name. See the name attribute definition in HTML 4.01.\n-\t *\n-\t * @return a {@link java.lang.String} object.\n-\t */\n-\tString getName();\n-\n-\t/**\n-\t * Select form of content. See the scheme attribute definition in HTML 4.01.\n-\t *\n-\t * @return a {@link java.lang.String} object.\n-\t */\n-\tString getScheme();\n-\n-\t/**\n-\t * Associated information. See the content attribute definition in HTML 4.01.\n-\t *\n-\t * @param content a {@link java.lang.String} object.\n-\t */\n-\tvoid setContent(String content);\n-\n-\t/**\n-\t * HTTP response header name [<a href='http://www.ietf.org/rfc/rfc2616.txt'>IETF\n-\t * RFC 2616</a>]. See the http-equiv attribute definition in HTML 4.01.\n-\t *\n-\t * @param httpEquiv a {@link java.lang.String} object.\n-\t */\n-\tvoid setHttpEquiv(String httpEquiv);\n-\n-\t/**\n-\t * Meta information name. See the name attribute definition in HTML 4.01.\n-\t *\n-\t * @param name a {@link java.lang.String} object.\n-\t */\n-\tvoid setName(String name);\n-\n-\t/**\n-\t * Select form of content. See the scheme attribute definition in HTML 4.01.\n-\t *\n-\t * @param scheme a {@link java.lang.String} object.\n-\t */\n-\tvoid setScheme(String scheme);\n-\n-}\n+    /**\n+     * Associated information. See the content attribute definition in HTML 4.01.\n+     *\n+     * @return a {@link java.lang.String} object.\n+     */\n+\n+\n+    String getContent();\n+\n+    /**\n+     * HTTP response header name [<a href='http://www.ietf.org/rfc/rfc2616.txt'>IETF\n+     * RFC 2616</a>]. See the http-equiv attribute definition in HTML 4.01.\n+     *\n+     * @return a {@link java.lang.String} object.\n+     */\n+\n+\n+    String getHttpEquiv();\n+\n+    /**\n+     * Meta information name. See the name attribute definition in HTML 4.01.\n+     *\n+     * @return a {@link java.lang.String} object.\n+     */\n+\n+\n+    String getName();\n+\n+    /**\n+     * Select form of content. See the scheme attribute definition in HTML 4.01.\n+     *\n+     * @return a {@link java.lang.String} object.\n+     */\n+\n+\n+    String getScheme();\n+\n+    /**\n+     * Associated information. See the content attribute definition in HTML 4.01.\n+     *\n+     * @param content a {@link java.lang.String} object.\n+     */\n+\n+\n+    void setContent(String content);\n+\n+    /**\n+     * HTTP response header name [<a href='http://www.ietf.org/rfc/rfc2616.txt'>IETF\n+     * RFC 2616</a>]. See the http-equiv attribute definition in HTML 4.01.\n+     *\n+     * @param httpEquiv a {@link java.lang.String} object.\n+     */\n+\n+\n+    void setHttpEquiv(String httpEquiv);\n+\n+    /**\n+     * Meta information name. See the name attribute definition in HTML 4.01.\n+     *\n+     * @param name a {@link java.lang.String} object.\n+     */\n+\n+\n+    void setName(String name);\n+\n+    /**\n+     * Select form of content. See the scheme attribute definition in HTML 4.01.\n+     *\n+     * @param scheme a {@link java.lang.String} object.\n+     */\n+\n+\n+    void setScheme(String scheme);\n+}\n\\ No newline at end of file\n",
            "diff_size": 76
        },
        {
            "tool": "styler_random",
            "errors": [
                {
                    "line": "48",
                    "column": "1",
                    "severity": "error",
                    "message": "File contains tab characters (this is the first instance).",
                    "source": "com.puppycrawl.tools.checkstyle.checks.whitespace.FileTabCharacterCheck"
                }
            ],
            "diff": "diff --git a/home/thomas/mnt/fernanda/styler-test2/python/./experiments/projects/../results/LoboEvolution-LoboEvolution/errored/1/115/HTMLMetaElement.java b/home/thomas/mnt/fernanda/styler-test2/python/./experiments/projects/../results/LoboEvolution-LoboEvolution/styler_random/115/HTMLMetaElement.java\nindex 6e6e51884b..71cf1a3909 100644\n--- a/home/thomas/mnt/fernanda/styler-test2/python/./experiments/projects/../results/LoboEvolution-LoboEvolution/errored/1/115/HTMLMetaElement.java\n+++ b/home/thomas/mnt/fernanda/styler-test2/python/./experiments/projects/../results/LoboEvolution-LoboEvolution/styler_random/115/HTMLMetaElement.java\n@@ -44,7 +44,7 @@ package org.loboevolution.html.dom;\n  * @version $Id: $Id\n  */\n public interface HTMLMetaElement extends HTMLElement {\n-\t/**\n+/**\n \t * Associated information. See the content attribute definition in HTML 4.01.\n \t *\n \t * @return a {@link java.lang.String} object.\n",
            "diff_size": 1
        },
        {
            "tool": "styler_three_grams",
            "errors": null,
            "diff": null
        }
    ]
}